sql_adapters/__init__.py
sql_adapters/connector.py
sql_adapters/py.typed
sql_adapters/sqlite.py
sql_adapters/utils.py
sql_adapters-0.3.0.dist-info/WHEEL
sql_adapters-0.3.0.dist-info/METADATA
sql_adapters-0.3.0.dist-info/RECORD
