Metadata-Version: 2.3
Name: sql-adapters
Version: 0.3.0
Summary: SQL adapters for various databases - SQLAlchemy simplifed
Author: jealouscloud
Author-email: jealouscloud <github@noaha.org>
Requires-Dist: sqlalchemy>=2.0.44
Requires-Python: >=3.10
